{
  "source": "NON_PICKUP_PRIORITIZED_IDEAS.md Rank 1-20",
  "rank": 6,
  "tier": "P0",
  "score": 70,
  "domain": "AssetPipeline",
  "ideaNo": 7,
  "ideaNo3": "007",
  "ideaName": "配信アセット依存グラフ",
  "repositoryName": "streaming-asset-dependency-graph",
  "publish": "GitHub Release / BOOTH",
  "priorityReason": "Addressablesや配信素材の依存可視化はUnity/Unreal制作で再利用性が高い。",
  "repoReadmeBeforeCreation": "存在しない",
  "exactCreatedIdeaFolder": "D:\\AI\\AssetPipeline\\created_idea_007_streaming-asset-dependency-graph",
  "exactZipPath": "D:\\AI\\AssetPipeline\\created_idea_007_streaming-asset-dependency-graph\\idea_007_streaming-asset-dependency-graph.zip",
  "exactMatch": true,
  "fallbackSearchUsed": false,
  "zipEntries": [
    "01_REQUIREMENTS.md",
    "02_SPECIFICATION.md",
    "03_DESIGN.md",
    "04_IMPLEMENTATION_PLAN.md",
    "05_TEST_PLAN.md",
    "06_RELEASE_CHECKLIST.md",
    "README.md",
    "START_PROMPT.md",
    "metadata.json"
  ],
  "metadataRepositoryName": "streaming-asset-dependency-graph",
  "metadataRepositoryMatches": true,
  "metadataDomain": "AssetPipeline",
  "metadataDomainMatches": true,
  "metadataIdea": "配信アセット依存グラフ",
  "metadataIntegration": "Unity Editor / Unreal Editor",
  "mojibakeHandling": "ZIP markdown は参照したが、正式 docs は NON PICKUP 行、metadata、ドメイン docs を根拠に正常な日本語で再構成した。",
  "adobeHost": null,
  "adobeHostReason": null
}
